pyscanfcs/__init__.py
pyscanfcs/__main__.py
pyscanfcs/_version.py
pyscanfcs/_version_save.py
pyscanfcs/bin_pe.cp36-win_amd64.pyd
pyscanfcs/bin_pe.pyx
pyscanfcs/fitting.py
pyscanfcs/openfile.py
pyscanfcs/util.py
pyscanfcs/gui_wx/PyScanFCS.py
pyscanfcs/gui_wx/__init__.py
pyscanfcs/gui_wx/doc.py
pyscanfcs/gui_wx/edclasses.py
pyscanfcs/gui_wx/icon.py
pyscanfcs/gui_wx/main.py
pyscanfcs/gui_wx/misc.py
pyscanfcs/gui_wx/uilayer.py
pyscanfcs-0.3.6.dist-info/LICENSE.txt
pyscanfcs-0.3.6.dist-info/METADATA
pyscanfcs-0.3.6.dist-info/RECORD
pyscanfcs-0.3.6.dist-info/WHEEL
pyscanfcs-0.3.6.dist-info/entry_points.txt
pyscanfcs-0.3.6.dist-info/top_level.txt
