Metadata-Version: 2.1
Name: pyscanfcs
Version: 0.3.6
Summary: Scientific tool for perpendicular line scanning FCS.
Home-page: https://github.com/FCS-analysis/PyScanFCS
Author: Paul Müller
Author-email: dev@craban.de
License: GPL v2
Keywords: fcs,fluorescence correlation spectroscopy,perpendicular line scanning,multiple-tau
Platform: ALL
Classifier: Operating System :: OS Independent
Classifier: Programming Language :: Python :: 3
Classifier: Topic :: Scientific/Engineering :: Visualization
Classifier: Intended Audience :: Science/Research
Requires-Python: >=3.4, <4
Requires-Dist: astropy
Requires-Dist: matplotlib (>=1.1.0)
Requires-Dist: multipletau (>=0.1.4)
Requires-Dist: numpy (>=1.5.1)
Requires-Dist: scipy (>=0.8.0)
Requires-Dist: tifffile (>=2020.5.25)
Requires-Dist: wxpython (>=4.0.3)
